test
sphinxcontrib
