Metadata-Version: 1.0
Name: sphinxcontrib-spam
Version: 0.4.2
Summary: output spam! spam! spam!
Home-page: https://github.com/jptomo/sphinxcontrib-spam
Author: Tomohiro Nakamura
Author-email: quickness.net at gmall.com
License: New BSD
Platform: any
Classifier: Development Status :: 4 - Beta
Classifier: License :: OSI Approved :: BSD License
Classifier: Operating System :: OS Independent
Classifier: Programming Language :: Python :: 2.6
Classifier: Programming Language :: Python :: 2.7
